odoo/addons/ssi_account_statement_import/README.rst
odoo/addons/ssi_account_statement_import/__init__.py
odoo/addons/ssi_account_statement_import/__manifest__.py
odoo/addons/ssi_account_statement_import/models/__init__.py
odoo/addons/ssi_account_statement_import/models/account_bank_statement.py
odoo/addons/ssi_account_statement_import/static/description/icon.png
odoo/addons/ssi_account_statement_import/static/src/xml/account_reconciliation.xml
odoo/addons/ssi_account_statement_import/test_file/sample_statement_idr.xlsx
odoo/addons/ssi_account_statement_import/views/account_bank_statement_views.xml
odoo/addons/ssi_account_statement_import/wizards/__init__.py
odoo/addons/ssi_account_statement_import/wizards/account_statement_import.py
odoo14_addon_ssi_account_statement_import-14.0.1.1.0.dist-info/METADATA
odoo14_addon_ssi_account_statement_import-14.0.1.1.0.dist-info/WHEEL
odoo14_addon_ssi_account_statement_import-14.0.1.1.0.dist-info/top_level.txt
odoo14_addon_ssi_account_statement_import-14.0.1.1.0.dist-info/RECORD
